aws_blackbelt_mcp_server/__init__.py
aws_blackbelt_mcp_server/config.py
aws_blackbelt_mcp_server/server.py
aws_blackbelt_mcp_server/helpers/__init__.py
aws_blackbelt_mcp_server/helpers/path_resolver.py
aws_blackbelt_mcp_server/scripts/inspect.py
aws_blackbelt_mcp_server/tools/__init__.py
aws_blackbelt_mcp_server/tools/seminars.py
aws_blackbelt_mcp_server-0.2.1.dist-info/METADATA
aws_blackbelt_mcp_server-0.2.1.dist-info/WHEEL
aws_blackbelt_mcp_server-0.2.1.dist-info/entry_points.txt
aws_blackbelt_mcp_server-0.2.1.dist-info/licenses/LICENSE
aws_blackbelt_mcp_server-0.2.1.dist-info/RECORD
