Metadata-Version: 2.4
Name: aws-blackbelt-mcp-server
Version: 0.2.1
Summary: Model Context Protocol (MCP) server for AWS Black Belt Online Seminar
Author-email: Konippi <konippi@amazon.co.jp>
License: Apache-2.0
License-File: LICENSE
Requires-Python: >=3.10
Requires-Dist: fastmcp>=2.12.3
Requires-Dist: httpx>=0.27.0
Requires-Dist: loguru>=0.7.3
Requires-Dist: mcp>=1.14.1
Requires-Dist: pydantic-settings>=2.10.1
Requires-Dist: youtube-transcript-api>=1.2.2
